aas_mcp/__init__.py
aas_mcp/__main__.py
aas_mcp/server.py
aas_mcp-0.0.1.dist-info/METADATA
aas_mcp-0.0.1.dist-info/WHEEL
aas_mcp-0.0.1.dist-info/entry_points.txt
aas_mcp-0.0.1.dist-info/licenses/LICENSE
aas_mcp-0.0.1.dist-info/RECORD
