Metadata-Version: 2.4
Name: aas-mcp
Version: 0.0.1
Summary: A Python Model Context Protocol (MCP) Server for Eclipse BaSyx to manage Asset Administration Shells (AAS)
Project-URL: Homepage, https://github.com/SmartFactory-KL/aas-mcp
Project-URL: Issues, https://github.com/SmartFactory-KL/aas-mcp/issues
Project-URL: Documentation, https://github.com/SmartFactory-KL/aas-mcp
Author-email: Peter Stein <peter.stein@dfki.de>
License: MIT License
License-File: LICENSE
Classifier: License :: OSI Approved :: MIT License
Classifier: Operating System :: OS Independent
Classifier: Programming Language :: Python :: 3
Classifier: Programming Language :: Python :: 3.10
Classifier: Programming Language :: Python :: 3.11
Classifier: Programming Language :: Python :: 3.12
Classifier: Programming Language :: Python :: 3.13
Requires-Python: >=3.10
Requires-Dist: fastmcp
Requires-Dist: shellsmith>=0.4.0
Provides-Extra: test
Requires-Dist: mypy; extra == 'test'
Requires-Dist: pytest; extra == 'test'
Requires-Dist: ruff; extra == 'test'
